drowsy_recorder/__init__.py
drowsy_recorder/build/index.html
drowsy_recorder-0.0.3.dist-info/METADATA
drowsy_recorder-0.0.3.dist-info/WHEEL
drowsy_recorder-0.0.3.dist-info/entry_points.txt
drowsy_recorder-0.0.3.dist-info/RECORD
