Metadata-Version: 2.1
Name: drowsy-recorder
Version: 0.0.3
Summary: 
Author: Gilad Kutiel
Author-email: giladk@mobileye.com
Requires-Python: >=3.10,<4.0
Classifier: Programming Language :: Python :: 3
Classifier: Programming Language :: Python :: 3.10
Classifier: Programming Language :: Python :: 3.11
Classifier: Programming Language :: Python :: 3.12
Requires-Dist: fastapi (>=0.111.1,<0.112.0)
Requires-Dist: ffmpegio (>=0.10.0.post0,<0.11.0)
Requires-Dist: opencv-python (>=4.10.0.84,<5.0.0.0)
Requires-Dist: tqdm (>=4.66.4,<5.0.0)
